Metadata-Version: 2.1
Name: h5imagegenerator
Version: 1.2.4
Summary: A dead simple Keras HDF5 ImageDataGenerator
Home-page: https://github.com/angulartist/Keras-HDF5-ImageDataGenerator
Author: @angulartist
Author-email: michel@kebab.io
License: BSD
Download-URL: https://github.com/angulartist/Keras-HDF5-ImageDataGenerator/tarball/1.2.4
Platform: UNKNOWN
Classifier: Development Status :: 5 - Production/Stable
Classifier: Intended Audience :: Science/Research
Classifier: Programming Language :: Python :: 3.6
Requires-Python: >=3
